[{"k":"62:1","a":1,"words":[{"t":"يُسَبِّحُ","r":"سبح"},{"t":"لِلَّهِ","r":"أله"},{"t":"مَا"},{"t":"فِى"},{"t":"ٱلسَّمَـٰوَٰتِ","r":"سمو"},{"t":"وَمَا"},{"t":"فِى"},{"t":"ٱلْأَرْضِ","r":"أرض"},{"t":"ٱلْمَلِكِ","r":"ملك"},{"t":"ٱلْقُدُّوسِ","r":"قدس"},{"t":"ٱلْعَزِيزِ","r":"عزز"},{"t":"ٱلْحَكِيمِ","r":"حكم"}]},{"k":"62:2","a":2,"words":[{"t":"هُوَ"},{"t":"ٱلَّذِى"},{"t":"بَعَثَ","r":"بعث"},{"t":"فِى"},{"t":"ٱلْأُمِّيِّـۧنَ","r":"أمم"},{"t":"رَسُولًا","r":"رسل"},{"t":"مِّنْهُمْ"},{"t":"يَتْلُوا۟","r":"تلو"},{"t":"عَلَيْهِمْ"},{"t":"ءَايَـٰتِهِۦ","r":"أيي"},{"t":"وَيُزَكِّيهِمْ","r":"زكو"},{"t":"وَيُعَلِّمُهُمُ","r":"علم"},{"t":"ٱلْكِتَـٰبَ","r":"كتب"},{"t":"وَٱلْحِكْمَةَ","r":"حكم"},{"t":"وَإِن"},{"t":"كَانُوا۟","r":"كون"},{"t":"مِن"},{"t":"قَبْلُ","r":"قبل"},{"t":"لَفِى"},{"t":"ضَلَـٰلٍ","r":"ضلل"},{"t":"مُّبِينٍ","r":"بين"}]},{"k":"62:3","a":3,"words":[{"t":"وَءَاخَرِينَ","r":"أخر"},{"t":"مِنْهُمْ"},{"t":"لَمَّا"},{"t":"يَلْحَقُوا۟","r":"لحق"},{"t":"بِهِمْ"},{"t":"ۚ"},{"t":"وَهُوَ"},{"t":"ٱلْعَزِيزُ","r":"عزز"},{"t":"ٱلْحَكِيمُ","r":"حكم"}]},{"k":"62:4","a":4,"words":[{"t":"ذَٰلِكَ"},{"t":"فَضْلُ","r":"فضل"},{"t":"ٱللَّهِ","r":"أله"},{"t":"يُؤْتِيهِ","r":"أتي"},{"t":"مَن"},{"t":"يَشَآءُ","r":"شيأ"},{"t":"ۚ"},{"t":"وَٱللَّهُ","r":"أله"},{"t":"ذُو"},{"t":"ٱلْفَضْلِ","r":"فضل"},{"t":"ٱلْعَظِيمِ","r":"عظم"}]},{"k":"62:5","a":5,"words":[{"t":"مَثَلُ","r":"مثل"},{"t":"ٱلَّذِينَ"},{"t":"حُمِّلُوا۟","r":"حمل"},{"t":"ٱلتَّوْرَىٰةَ"},{"t":"ثُمَّ"},{"t":"لَمْ"},{"t":"يَحْمِلُوهَا","r":"حمل"},{"t":"كَمَثَلِ","r":"مثل"},{"t":"ٱلْحِمَارِ","r":"حمر"},{"t":"يَحْمِلُ","r":"حمل"},{"t":"أَسْفَارًۢا","r":"سفر"},{"t":"ۚ"},{"t":"بِئْسَ","r":"بأس"},{"t":"مَثَلُ","r":"مثل"},{"t":"ٱلْقَوْمِ","r":"قوم"},{"t":"ٱلَّذِينَ"},{"t":"كَذَّبُوا۟","r":"كذب"},{"t":"بِـَٔايَـٰتِ","r":"أيي"},{"t":"ٱللَّهِ","r":"أله"},{"t":"ۚ"},{"t":"وَٱللَّهُ","r":"أله"},{"t":"لَا"},{"t":"يَهْدِى","r":"هدي"},{"t":"ٱلْقَوْمَ","r":"قوم"},{"t":"ٱلظَّـٰلِمِينَ","r":"ظلم"}]},{"k":"62:6","a":6,"words":[{"t":"قُلْ","r":"قول"},{"t":"يَـٰٓأَيُّهَا","r":"أيي"},{"t":"ٱلَّذِينَ"},{"t":"هَادُوٓا۟","r":"هود"},{"t":"إِن"},{"t":"زَعَمْتُمْ","r":"زعم"},{"t":"أَنَّكُمْ"},{"t":"أَوْلِيَآءُ","r":"ولي"},{"t":"لِلَّهِ","r":"أله"},{"t":"مِن"},{"t":"دُونِ","r":"دون"},{"t":"ٱلنَّاسِ","r":"أنس"},{"t":"فَتَمَنَّوُا۟","r":"مني"},{"t":"ٱلْمَوْتَ","r":"موت"},{"t":"إِن"},{"t":"كُنتُمْ","r":"كون"},{"t":"صَـٰدِقِينَ","r":"صدق"}]},{"k":"62:7","a":7,"words":[{"t":"وَلَا"},{"t":"يَتَمَنَّوْنَهُۥٓ","r":"مني"},{"t":"أَبَدًۢا","r":"أبد"},{"t":"بِمَا"},{"t":"قَدَّمَتْ","r":"قدم"},{"t":"أَيْدِيهِمْ","r":"يدي"},{"t":"ۚ"},{"t":"وَٱللَّهُ","r":"أله"},{"t":"عَلِيمٌۢ","r":"علم"},{"t":"بِٱلظَّـٰلِمِينَ","r":"ظلم"}]},{"k":"62:8","a":8,"words":[{"t":"قُلْ","r":"قول"},{"t":"إِنَّ"},{"t":"ٱلْمَوْتَ","r":"موت"},{"t":"ٱلَّذِى"},{"t":"تَفِرُّونَ","r":"فرر"},{"t":"مِنْهُ"},{"t":"فَإِنَّهُۥ"},{"t":"مُلَـٰقِيكُمْ","r":"لقي"},{"t":"ۖ"},{"t":"ثُمَّ"},{"t":"تُرَدُّونَ","r":"ردد"},{"t":"إِلَىٰ"},{"t":"عَـٰلِمِ","r":"علم"},{"t":"ٱلْغَيْبِ","r":"غيب"},{"t":"وَٱلشَّهَـٰدَةِ","r":"شهد"},{"t":"فَيُنَبِّئُكُم","r":"نبأ"},{"t":"بِمَا"},{"t":"كُنتُمْ","r":"كون"},{"t":"تَعْمَلُونَ","r":"عمل"}]},{"k":"62:9","a":9,"words":[{"t":"يَـٰٓأَيُّهَا","r":"أيي"},{"t":"ٱلَّذِينَ"},{"t":"ءَامَنُوٓا۟","r":"أمن"},{"t":"إِذَا"},{"t":"نُودِىَ","r":"ندي"},{"t":"لِلصَّلَوٰةِ","r":"صلو"},{"t":"مِن"},{"t":"يَوْمِ","r":"يوم"},{"t":"ٱلْجُمُعَةِ","r":"جمع"},{"t":"فَٱسْعَوْا۟","r":"سعي"},{"t":"إِلَىٰ"},{"t":"ذِكْرِ","r":"ذكر"},{"t":"ٱللَّهِ","r":"أله"},{"t":"وَذَرُوا۟","r":"وذر"},{"t":"ٱلْبَيْعَ","r":"بيع"},{"t":"ۚ"},{"t":"ذَٰلِكُمْ"},{"t":"خَيْرٌ","r":"خير"},{"t":"لَّكُمْ"},{"t":"إِن"},{"t":"كُنتُمْ","r":"كون"},{"t":"تَعْلَمُونَ","r":"علم"}]},{"k":"62:10","a":10,"words":[{"t":"فَإِذَا"},{"t":"قُضِيَتِ","r":"قضي"},{"t":"ٱلصَّلَوٰةُ","r":"صلو"},{"t":"فَٱنتَشِرُوا۟","r":"نشر"},{"t":"فِى"},{"t":"ٱلْأَرْضِ","r":"أرض"},{"t":"وَٱبْتَغُوا۟","r":"بغي"},{"t":"مِن"},{"t":"فَضْلِ","r":"فضل"},{"t":"ٱللَّهِ","r":"أله"},{"t":"وَٱذْكُرُوا۟","r":"ذكر"},{"t":"ٱللَّهَ","r":"أله"},{"t":"كَثِيرًا","r":"كثر"},{"t":"لَّعَلَّكُمْ"},{"t":"تُفْلِحُونَ","r":"فلح"}]},{"k":"62:11","a":11,"words":[{"t":"وَإِذَا"},{"t":"رَأَوْا۟","r":"رأي"},{"t":"تِجَـٰرَةً","r":"تجر"},{"t":"أَوْ"},{"t":"لَهْوًا","r":"لهو"},{"t":"ٱنفَضُّوٓا۟","r":"فضض"},{"t":"إِلَيْهَا"},{"t":"وَتَرَكُوكَ","r":"ترك"},{"t":"قَآئِمًا","r":"قوم"},{"t":"ۚ"},{"t":"قُلْ","r":"قول"},{"t":"مَا"},{"t":"عِندَ","r":"عند"},{"t":"ٱللَّهِ","r":"أله"},{"t":"خَيْرٌ","r":"خير"},{"t":"مِّنَ"},{"t":"ٱللَّهْوِ","r":"لهو"},{"t":"وَمِنَ"},{"t":"ٱلتِّجَـٰرَةِ","r":"تجر"},{"t":"ۚ"},{"t":"وَٱللَّهُ","r":"أله"},{"t":"خَيْرُ","r":"خير"},{"t":"ٱلرَّٰزِقِينَ","r":"رزق"}]}]