{
    "language_insights": [
        {
            "formatted_ayah_ref": "43_10",
            "details": [
                {
                    "part_num": 1,
                    "text": "<br>Derivative: مَهْدًا – A place of comfort, cradle or smooth flooring. <br> ",
                    "insight_type": "word",
                    "arabic_part": "مَهْدًا"
                }
            ]
        },
        {
            "formatted_ayah_ref": "43_11",
            "details": [
                {
                    "part_num": 1,
                    "text": "<br>Derivative: أَنشَرْنَا from أَنْشَرَ which means to raise up. Here it means to revive, resurrect or bring the land to life through water. <br> ",
                    "insight_type": "word",
                    "arabic_part": "فَأَنشَرْنَا"
                }
            ]
        },
        {
            "formatted_ayah_ref": "43_13",
            "details": [
                {
                    "part_num": 1,
                    "text": "<br>Derivative: مُقْرِنِينَ from أَقْرَنَ which means to have power and control over something.<br> ",
                    "insight_type": "word",
                    "arabic_part": "مُقْرِنِينَ"
                },
                {
                    "part_num": 2,
                    "text": "<br>Derivative: تَسْتَوُوا from اِسْتَوَى which means to set yourself upright and even referring here to mounting a riding animal and sitting firmly and evenly upon it. ",
                    "insight_type": "word",
                    "arabic_part": "لِتَسْتَوُۥا۟"
                }
            ]
        },
        {
            "formatted_ayah_ref": "43_15",
            "details": [
                {
                    "part_num": 1,
                    "text": "<br>Derivative: جُزْءًا means a part or portion (of something). Here it is being used to refer to the attribution of offspring to Allah. جُزْءًا means something that is attributed to Him as if it is a part of Him.<br> ",
                    "insight_type": "word",
                    "arabic_part": "جُزْءًا"
                }
            ]
        },
        {
            "formatted_ayah_ref": "43_17",
            "details": [
                {
                    "part_num": 1,
                    "text": "<br>Derivative: كَظِيمٌ means to swallow or suppress one’s rage or grief.<br> ",
                    "insight_type": "word",
                    "arabic_part": "كَظِيمٌ"
                }
            ]
        },
        {
            "formatted_ayah_ref": "43_20",
            "details": [
                {
                    "part_num": 1,
                    "text": "<br>Derivative: يَخْرُصُونَ from خَرَصَ which means to make wild guesses or to make uninformed conjectures. خَرَّاص is the person who makes statements or forms conclusions based on pure conjecture and guessing without having any proof to back them up i.e., to make something up whilst making it sound compelling.<br> ",
                    "insight_type": "word",
                    "arabic_part": "يَخْرُصُونَ"
                }
            ]
        },
        {
            "formatted_ayah_ref": "43_21",
            "details": [
                {
                    "part_num": 1,
                    "text": "<br>Derivative: مُسْتَمْسِكُونَ from اِسْتَمْسَكَ – اِسْتِمْسَاك which means to hold onto tightly or firmly. <br> ",
                    "insight_type": "word",
                    "arabic_part": "مُسْتَمْسِكُونَ"
                }
            ]
        },
        {
            "formatted_ayah_ref": "43_22",
            "details": [
                {
                    "part_num": 1,
                    "text": "<br>Derivative: أُمَّةٍ refers to a nation and legacy. Here it implies a direction, path and singular focus.<br> ",
                    "insight_type": "word",
                    "arabic_part": "أُمَّةٍ"
                }
            ]
        },
        {
            "formatted_ayah_ref": "43_23",
            "details": [
                {
                    "part_num": 1,
                    "text": "<br>Derivative: مُتْرَفُو which is مُتْرَفُونَ are those who are blinded and corrupted by their great wealth and luxury. ",
                    "insight_type": "word",
                    "arabic_part": "مُتْرَفُوهَآ"
                },
                {
                    "part_num": 2,
                    "text": "<br>Derivative: مُّقْتَدُونَ from اِقْتَدَى refers to those who are committed to following and proceeding along the same path, model or example as others. Those who emulate others.<br> ",
                    "insight_type": "word",
                    "arabic_part": "مُّقْتَدُونَ"
                }
            ]
        },
        {
            "formatted_ayah_ref": "43_25",
            "details": [
                {
                    "part_num": 1,
                    "text": "<br>Derivative: الْمُكَذِّبِينَ – المُكَذِّبُ from كَذَّبَ is someone who calls something else a lie and denies it.<br> ",
                    "insight_type": "word",
                    "arabic_part": "ٱلْمُكَذِّبِينَ"
                }
            ]
        },
        {
            "formatted_ayah_ref": "43_26",
            "details": [
                {
                    "part_num": 1,
                    "text": "<br>Derivative: بَرَاءٌ means to be free from something and a declaration of not having any association with something or a renunciation of it. It is more powerful than بَريءٌ. بَرَاءٌ can be used with the singular, dual and plural without change.<br> ",
                    "insight_type": "word",
                    "arabic_part": "بَرَآءٌ"
                }
            ]
        },
        {
            "formatted_ayah_ref": "43_3",
            "details": [
                {
                    "part_num": 1,
                    "text": "<br>Derivative: جَعَلْنَا – From جَعَلَ which means to make. In Arabic جَعَلَ (to make) has a different meaning to خَلَقَ which is to create. جَعَلَ (Ja’ala) means to make in respect to something that is already there and to transform it or its use or function whilst خَلَق means to make something from nothing that did not previously exist.<br> ",
                    "insight_type": "word",
                    "arabic_part": "جَعَلْنَٰهُ"
                }
            ]
        },
        {
            "formatted_ayah_ref": "43_33",
            "details": [
                {
                    "part_num": 1,
                    "text": "<br>Derivative: مَعَارِجَ means levels by which you ascend higher. It is used in Arabic to refer to stairways. <br> ",
                    "insight_type": "word",
                    "arabic_part": "وَمَعَارِجَ"
                }
            ]
        },
        {
            "formatted_ayah_ref": "43_35",
            "details": [
                {
                    "part_num": 1,
                    "text": "<br>Derivative: لَمَّا – In this verse لَمَّا carries the unique meaning of إِلَّا (except or apart from) instead of its usual meaning of “when” or “not” when used before the present tense verb.<br> ",
                    "insight_type": "word",
                    "arabic_part": "لَمَّا"
                },
                {
                    "part_num": 2,
                    "text": "<br>Derivative: زُخْرُفًا is something that resembles gold in terms of being shiny and glittery. It refers to the shiny materials which are used to adorn. In this case to adorn the house.",
                    "insight_type": "word",
                    "arabic_part": "وَزُخْرُفًا"
                }
            ]
        },
        {
            "formatted_ayah_ref": "43_36",
            "details": [
                {
                    "part_num": 1,
                    "text": "<br>Derivative: يَعْشُ from عَشَا – يَعْشُو which means to ignore, not pay attention to or to turn away from something. The original meaning of عَشَا is to have weak eyesight whereby he is unable to discern something. Consequently, he ignores it and doesn’t pay attention to it. <br> ",
                    "insight_type": "word",
                    "arabic_part": "يَعْشُ"
                }
            ]
        },
        {
            "formatted_ayah_ref": "43_38",
            "details": [
                {
                    "part_num": 1,
                    "text": "<br>Derivative: الْمَشْرِقَيْنِ – It literally means the “Two places where the sun rises” and implies an impossible distance i.e., something so far that it cannot be reached. As such, it means two impossible distances to emphasis the greatness of the distance. The majority view however is that الْمَشْرِقَيْنِ \"The two places of sunrise or two Easts\" refers to the \"Place of sunrise (or the East) and the place of sunset (or the West)” (Al-Mashriq (المَشْرِق) and Al-Maghrib (المَغْرِب)). This is because In the Arabic language when there are pairs of something they can both be referred to by using the dual form of one of them. As such the distance between الْمَشْرِقَيْنِ is an expression meaning the distance between the East and the West.<br> ",
                    "insight_type": "word",
                    "arabic_part": "ٱلْمَشْرِقَيْنِ"
                }
            ]
        },
        {
            "formatted_ayah_ref": "43_4",
            "details": [
                {
                    "part_num": 1,
                    "text": "<br>- أُمِّ الْكِتَابِ (Umm il-Kitaab) literally means “The mother of the Book” referring to اللَّوْحُ المَحْفُوظ (The preserved tablet). <br> ",
                    "insight_type": "phrase",
                    "arabic_part": "أُمِّ الْكِتَابِ"
                }
            ]
        },
        {
            "formatted_ayah_ref": "43_42",
            "details": [
                {
                    "part_num": 1,
                    "text": "<br>Derivative: مُّقْتَدِرُونَ – مُقْتَدِر refers to a greater level of control, capability and power than قَدِير. مُقْتَدِر is someone who has absolute control over something.<br> ",
                    "insight_type": "word",
                    "arabic_part": "مُّقْتَدِرُونَ"
                }
            ]
        },
        {
            "formatted_ayah_ref": "43_5",
            "details": [
                {
                    "part_num": 1,
                    "text": "<br>Derivative: صَفْحًا from صَفَحَ which means to turn away, to snub, cast aside or disregard something or somebody. ",
                    "insight_type": "word",
                    "arabic_part": "صَفْحًا"
                },
                {
                    "part_num": 2,
                    "text": "<br>Derivative: نَضْرِبُ from ضَرَبَ means to strike. When followed by عَن it means to turn away from, abandon, leave or neglect something.",
                    "insight_type": "word",
                    "arabic_part": "أَفَنَضْرِبُ"
                },
                {
                    "part_num": 3,
                    "text": "<br>- ضَربَ عَن ... صَفْحاً when used together صَفْحًا is used to emphasise ضَربَ عَن i.e., Should we just completely cast aside giving you the Dhikr (reminder) because …<br> ",
                    "insight_type": "phrase",
                    "arabic_part": "أَفَنَضْرِبُ عَنكُمُ الذِّكْرَ صَفْحًا"
                }
            ]
        },
        {
            "formatted_ayah_ref": "43_50",
            "details": [
                {
                    "part_num": 1,
                    "text": "<br>Derivative: يَنكُثُونَ from نَكَثَ which means to go back on an agreement or one’s word. To violate and break the agreement.<br> ",
                    "insight_type": "word",
                    "arabic_part": "يَنكُثُونَ"
                }
            ]
        },
        {
            "formatted_ayah_ref": "43_54",
            "details": [
                {
                    "part_num": 1,
                    "text": "<br>Derivative: اسْتَخَفَّ means to attempt to make people dumb, make light of someone and take away their ability to think. It means to attempt to befool and mislead by playing on people’s ignorance – to attempt to sway by propaganda. <br> ",
                    "insight_type": "word",
                    "arabic_part": "فَٱسْتَخَفَّ"
                }
            ]
        },
        {
            "formatted_ayah_ref": "43_56",
            "details": [
                {
                    "part_num": 1,
                    "text": "<br>Derivative: سَلَفًا means something that is behind, in the past or has preceded. Here it refers to Fir’awn and his people and means that “We made them a precedent from the past”.<br> ",
                    "insight_type": "word",
                    "arabic_part": "سَلَفًا"
                }
            ]
        },
        {
            "formatted_ayah_ref": "43_57",
            "details": [
                {
                    "part_num": 1,
                    "text": "<br>Derivative: يَصِدُّونَ means to raise their voices with laughing and mockery – to jeer. <br> ",
                    "insight_type": "word",
                    "arabic_part": "يَصِدُّونَ"
                }
            ]
        },
        {
            "formatted_ayah_ref": "43_60",
            "details": [
                {
                    "part_num": 1,
                    "text": "<br>Derivative: يَخْلُفُونَ from خَلَفَ which means to come one after another or succeed one another.<br> ",
                    "insight_type": "word",
                    "arabic_part": "يَخْلُفُونَ"
                }
            ]
        },
        {
            "formatted_ayah_ref": "43_61",
            "details": [
                {
                    "part_num": 1,
                    "text": "<br>Derivative: عِلْمٌ means knowledge and here it means that ‘Isa (as) will be a “knowledge of” (عِلْم) the coming of the final hour i.e., a known sign.<br> ",
                    "insight_type": "word",
                    "arabic_part": "عِلْمٌ"
                }
            ]
        },
        {
            "formatted_ayah_ref": "43_67",
            "details": [
                {
                    "part_num": 1,
                    "text": "<br>Derivative: الْأَخِلَّاءُ means the closets friends and is the plural of خَلِيل which is from the words indicating to the closest forms of friendship. <br> ",
                    "insight_type": "word",
                    "arabic_part": "ٱلْأَخِلَّآءُ"
                }
            ]
        },
        {
            "formatted_ayah_ref": "43_70",
            "details": [
                {
                    "part_num": 1,
                    "text": "<br>Derivative: تُحْبَرُونَ comes from the word حُبورٌ which means extreme happiness and joy – a level of happiness where nothing can cause you upset. تُحْبَرُونَ is in the passive case (مَجْهول) which indicates that it is a happiness that has been instilled into you.<br> ",
                    "insight_type": "word",
                    "arabic_part": "تُحْبَرُونَ"
                }
            ]
        },
        {
            "formatted_ayah_ref": "43_71",
            "details": [
                {
                    "part_num": 1,
                    "text": "<br>Derivative: صِحَافٍ are large trays or plates (for food). It is the plural of صَحْفَةٌ which is a large wide plate, the type which a whole family can eat from.",
                    "insight_type": "word",
                    "arabic_part": "بِصِحَافٍ"
                },
                {
                    "part_num": 2,
                    "text": "<br>Derivative: تَلَذُّ from لَذَ – لَذِيذٌ which means to be delicious and usually refers to the delight and satisfaction of the tongue. Here it is connected to the eyes i.e., that which pleases and delights them.<br> ",
                    "insight_type": "word",
                    "arabic_part": "وَتَلَذُّ"
                }
            ]
        },
        {
            "formatted_ayah_ref": "43_75",
            "details": [
                {
                    "part_num": 1,
                    "text": "<br>Derivative: يُفَتَّرُ from فَتَّرَ which means to give a فَتْرَةٌ which is a period of time, a break or cool off period i.e., the punishment of hell will not abate or be lightened for them. ",
                    "insight_type": "word",
                    "arabic_part": "يُفَتَّرُ"
                },
                {
                    "part_num": 2,
                    "text": "<br>Derivative: مُبْلِسُونَ in a state of complete hopelessness or abject despair. <br> ",
                    "insight_type": "word",
                    "arabic_part": "مُبْلِسُونَ"
                }
            ]
        },
        {
            "formatted_ayah_ref": "43_77",
            "details": [
                {
                    "part_num": 1,
                    "text": "<br>Derivative: مَّاكِثُونَ from مَكَثَ which means to remain and linger in a place. مَّاكِثُونَ means “Those who linger and remain”.<br> ",
                    "insight_type": "word",
                    "arabic_part": "مَّٰكِثُونَ"
                }
            ]
        },
        {
            "formatted_ayah_ref": "43_79",
            "details": [
                {
                    "part_num": 1,
                    "text": "<br>Derivative: أَبْرَمُوا from أَبْرَمَ which in origin was used to mean the twisting of rope together to make a strong knot and to make it hold fast. Here it refers to devising a plot or scheme that is precise, solid and strong.  <br> ",
                    "insight_type": "word",
                    "arabic_part": "أَبْرَمُوٓا۟"
                }
            ]
        },
        {
            "formatted_ayah_ref": "43_8",
            "details": [
                {
                    "part_num": 1,
                    "text": "<br>Derivative: بَطْشًا from بَطَشَ which means to grab hold with force, to punish, act violently and ruthlessly. <br> ",
                    "insight_type": "word",
                    "arabic_part": "بَطْشًا"
                }
            ]
        },
        {
            "formatted_ayah_ref": "43_83",
            "details": [
                {
                    "part_num": 1,
                    "text": "<br>Derivative: يَخُوضُوا from خَاضَ – خَوْضٌ which means to plunge or delve into something. Here it refers to engaging or delving in false speech and nonsense i.e., to waste time and not be serious in discussion.<br> ",
                    "insight_type": "word",
                    "arabic_part": "يَخُوضُوا۟"
                }
            ]
        },
        {
            "formatted_ayah_ref": "43_84",
            "details": [
                {
                    "part_num": 1,
                    "text": "<br>Derivative: السَّمَاءِ means the sky but is also general and undefined in terms of referring to that which is above.<br> ",
                    "insight_type": "word",
                    "arabic_part": "ٱلسَّمَآءِ"
                }
            ]
        },
        {
            "formatted_ayah_ref": "43_85",
            "details": [
                {
                    "part_num": 1,
                    "text": "<br>Derivative: تَبَارَكَ means to be full of بَرَكَةٌ (blessing) and the power to dispose of بَرَكَةٌ (Barakah). There are two matters related to the word بَرَكَةٌ. The first is what it implies in terms of the increase in goodness (Al-Khair) and more goodness coming than is expected. The second is the extraction of Al-Khair (goodness) and to bring good out of something that has the potential inside. Like the seed cannot produce its goodness until water has been provided to it and in doing so becomes “Mubaarak” water. تَبَارَكَ can be understood to mean: “And how full of Barakah and the power of blessing is He who …”.<br> ",
                    "insight_type": "word",
                    "arabic_part": "تَبَارَكَ"
                }
            ]
        },
        {
            "formatted_ayah_ref": "43_88",
            "details": [
                {
                    "part_num": 1,
                    "text": "<br>Derivative: قِيلِ is the Masdar (مَصْدَر) of قالَ like قَوْلٌ and قالٌ. It means: “Statement” or “That which is said”. <br> ",
                    "insight_type": "word",
                    "arabic_part": "وَقِيلِهِۦ"
                }
            ]
        }
    ]
}